hist/__init__.py
hist/accumulators.py
hist/axestuple.py
hist/basehist.py
hist/classichist.py
hist/hist.py
hist/interop.py
hist/intervals.py
hist/namedhist.py
hist/numpy.py
hist/plot.py
hist/py.typed
hist/quick_construct.py
hist/stack.py
hist/storage.py
hist/svgplots.py
hist/svgutils.py
hist/tag.py
hist/version.py
hist/version.pyi
hist/_compat/__init__.py
hist/_compat/builtins.py
hist/_compat/typing.py
hist/axis/__init__.py
hist/axis/py.typed
hist/axis/transform.py
hist/dask/__init__.py
hist/dask/hist.py
hist/dask/namedhist.py
hist/serialization/__init__.py
hist-2.9.1.dist-info/METADATA
hist-2.9.1.dist-info/WHEEL
hist-2.9.1.dist-info/entry_points.txt
hist-2.9.1.dist-info/licenses/LICENSE
hist-2.9.1.dist-info/RECORD
