Metadata-Version: 2.4
Name: hist
Version: 2.9.1
Summary: Hist classes and utilities
Project-URL: Homepage, https://github.com/scikit-hep/hist
Project-URL: Documentation, https://hist.readthedocs.io/
Project-URL: Bug Tracker, https://github.com/scikit-hep/hist/issues
Project-URL: Discussions, https://github.com/scikit-hep/hist/discussions
Project-URL: Changelog, https://hist.readthedocs.io/en/latest/changelog.html
Author-email: Henry Schreiner <henry.schreiner@cern.ch>, Aman Goel <aman.goel185@gmail.com>, Shuo Liu <ninomyemail@gmail.com>
Maintainer-email: The Scikit-HEP admins <scikit-hep-admins@googlegroups.com>
License-Expression: BSD-3-Clause
License-File: LICENSE
Keywords: boost-histogram,dask-histogram,histogram
Classifier: Development Status :: 5 - Production/Stable
Classifier: Intended Audience :: Developers
Classifier: Intended Audience :: Science/Research
Classifier: Operating System :: OS Independent
Classifier: Programming Language :: Python
Classifier: Programming Language :: Python :: 3
Classifier: Programming Language :: Python :: 3 :: Only
Classifier: Programming Language :: Python :: 3.9
Classifier: Programming Language :: Python :: 3.10
Classifier: Programming Language :: Python :: 3.11
Classifier: Programming Language :: Python :: 3.12
Classifier: Programming Language :: Python :: 3.13
Classifier: Programming Language :: Python :: 3.14
Classifier: Topic :: Scientific/Engineering
Classifier: Topic :: Scientific/Engineering :: Information Analysis
Classifier: Topic :: Scientific/Engineering :: Mathematics
Classifier: Topic :: Scientific/Engineering :: Physics
Classifier: Typing :: Typed
Requires-Python: >=3.9
Requires-Dist: boost-histogram<1.7,>=1.5
Requires-Dist: histoprint>=2.2.0
Requires-Dist: numpy>=1.19.3
Requires-Dist: typing-extensions>=4; python_version < '3.11'
Provides-Extra: dask
Requires-Dist: dask-histogram>=2023.1; extra == 'dask'
Requires-Dist: dask[dataframe]<2025,>=2022; extra == 'dask'
Provides-Extra: fit
Requires-Dist: iminuit>=2; extra == 'fit'
Requires-Dist: scipy>=1.5.4; extra == 'fit'
Provides-Extra: mpl
Requires-Dist: matplotlib>=3.8; extra == 'mpl'
Requires-Dist: mplhep>=0.3.33; extra == 'mpl'
Provides-Extra: plot
Requires-Dist: matplotlib>=3.8; extra == 'plot'
Requires-Dist: mplhep>=0.3.33; extra == 'plot'
